codepso/utils/__init__.py
codepso/utils/datagrid/datagrid.py
codepso/utils/datagrid/filters.py
codepso/utils/datagrid/paginator.py
codepso/utils/datagrid/query_builder.py
codepso/utils/datagrid/query_params.py
codepso_utils-0.1.1.dist-info/METADATA
codepso_utils-0.1.1.dist-info/WHEEL
codepso_utils-0.1.1.dist-info/RECORD
